aics_bead_alignment_core/__init__.py
aics_bead_alignment_core/align_utils.py
aics_bead_alignment_core/bin/__init__.py
aics_bead_alignment_core/bin/align_cli.py
aics_bead_alignment_core/conversions/conversions.py
aics_bead_alignment_core/tests/__init__.py
aics_bead_alignment_core-1.2.0.dist-info/LICENSE
aics_bead_alignment_core-1.2.0.dist-info/METADATA
aics_bead_alignment_core-1.2.0.dist-info/WHEEL
aics_bead_alignment_core-1.2.0.dist-info/entry_points.txt
aics_bead_alignment_core-1.2.0.dist-info/top_level.txt
aics_bead_alignment_core-1.2.0.dist-info/RECORD
